tbank_kassa/__init__.py
tbank_kassa/api.py
tbank_kassa/client.py
tbank_kassa/enums.py
tbank_kassa/logger.py
tbank_kassa/models/__init__.py
tbank_kassa/models/dicts/__init__.py
tbank_kassa/models/dicts/init.py
tbank_kassa/models/fields.py
tbank_kassa/models/request/__init__.py
tbank_kassa/models/request/client_info.py
tbank_kassa/models/request/enums.py
tbank_kassa/models/request/init.py
tbank_kassa/models/request/item_ffd_105.py
tbank_kassa/models/request/item_ffd_12.py
tbank_kassa/models/request/receipt_ffd_105.py
tbank_kassa/models/request/receipt_ffd_12.py
tbank_kassa/models/request/request.py
tbank_kassa/models/request/shop.py
tbank_kassa/models/response/__init__.py
tbank_kassa/models/response/payment.py
tbank_kassa/models/response/response.py
tbank_kassa/types.py
tbank_kassa-0.3.5.dist-info/METADATA
tbank_kassa-0.3.5.dist-info/WHEEL
tbank_kassa-0.3.5.dist-info/RECORD
