Metadata-Version: 2.3
Name: tbank-kassa
Version: 0.3.5
Summary: 
Author: Rostislaww
Author-email: rostiki.com@mail.ru
Requires-Python: >=3.11,<4.0
Classifier: Programming Language :: Python :: 3
Classifier: Programming Language :: Python :: 3.11
Classifier: Programming Language :: Python :: 3.12
Classifier: Programming Language :: Python :: 3.13
Requires-Dist: aiohttp (>=3.11.10,<4.0.0)
Requires-Dist: pydantic[email] (>=2.10.6,<3.0.0)
Requires-Dist: requests (>=2.32.3,<3.0.0)
Project-URL: Homepage, https://github.com/RostHarcha/tbank_kassa
